{"success":true,"data":{"total_record":1,"per_page":1,"total_page":1,"current_page":1,"result":[{"kode_PUM":"3308022008","provinsi":"Jawa Tengah","kabupaten_kota":"Kab. Magelang","kecamatan":"Borobudur","desa_kelurahan":"Candirejo","updated_date":null,"pagu":1010984000,"total_penyaluran":758238000,"penyaluran":{"1":{"realisasi":408716400,"tanggal_realisasi":"15-APR-20"},"2":{"realisasi":151647600,"tanggal_realisasi":"20-MAY-20"},"3":{"realisasi":197874000,"tanggal_realisasi":"11-NOV-20"}},"penyerapan":{"1":[{"nama":"Pembinaan Kemasyarakatan Desa","kegiatan":[{"nama":"Pembinaan Karang Taruna\/Klub Kepemudaan\/Klub Olah raga","uraian":[{"nama":"Terselenggaranya Pembinaan Karang Taruna\/Klub Kepemudaan\/Klub Olah raga","realisasi":18662950,"anggaran":18662950}]},{"nama":"Pemeliharaan Sarana dan Prasarana Kebudayaan\/Rumah Adat\/Keagamaan Milik Desa **","uraian":[{"nama":"Pemeliharaan Sarana dan Prasarana Kebudayaan\/Rumah Adat\/Keagamaan Milik Desa","realisasi":22427600,"anggaran":22427600}]}]},{"nama":"Pelaksanaan Pembangunan Desa","kegiatan":[{"nama":"Pemeliharaan Monumen\/Gapura\/Batas Desa","uraian":[{"nama":"Pemeliharaan Monumen\/Gapura\/Batas Desa","realisasi":8614045,"anggaran":8614045}]},{"nama":"Pembangunan\/Rehabilitasi\/Peningkatan Monumen\/Gapura\/Batas Desa **","uraian":[{"nama":"Monumen\/Gapura\/Batas Desa","realisasi":7848270,"anggaran":7848270}]},{"nama":"Dukungan pelaksanaan program Pembangunan\/Rehab Rumah Tidak Layak Huni (RTLH) GAKIN (pemetaan, validasi, dll)","uraian":[{"nama":"Jumlah Rumah Tidak Layak Huni (RTLH)","realisasi":12280570,"anggaran":12280570}]},{"nama":"Pemeliharaan Jalan Lingkungan Permukiman\/Gang","uraian":[{"nama":"Pemeliharaan Jalan Lingkungan Permukiman\/Gang","realisasi":18222935,"anggaran":18222935}]},{"nama":"Pengelolaan Lingkungan Hidup Desa","uraian":[{"nama":"Terselenggaranya Pengelolaan Lingkungan Hidup Desa Lainnya","realisasi":37155000,"anggaran":37155000}]},{"nama":"Pemeliharaan Sumur Resapan Milik Desa","uraian":[{"nama":"Pemeliharaan Sumur Serapan","realisasi":3118136,"anggaran":3118136}]},{"nama":"Pembangunan\/Rehabilitasi\/Peningkatan Sarana dan Prasarana Pariwisata Milik Desa **","uraian":[{"nama":"Sarana dan Prasarana Pariwisata Milik Desa","realisasi":19591670,"anggaran":19591670}]},{"nama":"Pemeliharaan Prasarana Jalan Desa (Gorong-gorong, Selokan, Box\/Slab Culvert, Drainase, Prasarana Jalan lain)","uraian":[{"nama":"Pemeliharaan Prasarana Jalan Desa (Gorong-gorong, Selokan, Box\/Slab Culvert, Drainase, Prasarana Jalan lain)","realisasi":22100000,"anggaran":22100000}]},{"nama":"Pemeliharaan Fasilitas Jamban Umum\/MCK umum, dll","uraian":[{"nama":"Pemeliharaan Fasilitas Jamban Umum\/MCK umum, dll","realisasi":26862200,"anggaran":26862200}]}]},{"nama":"Penyelenggaraan Pemerintahan Desa","kegiatan":[{"nama":"Pemeliharaan Gedung\/Prasarana Kantor Desa","uraian":[{"nama":"Pemeliharaan Gedung dan Prasarana Perkantoran","realisasi":32772220,"anggaran":32772220}]},{"nama":"Pembangunan\/Rehabilitasi\/Peningkatan Gedung\/Prasarana Kantor Desa**","uraian":[{"nama":"Rehabilitasi\/Peningkatan Bangunan","realisasi":14350805,"anggaran":14350805}]}]},{"nama":"Penanggulangan Bencana, Keadaan Darurat Dan Mendesak Desa","kegiatan":[{"nama":"Penanggulangan Bencana","uraian":[{"nama":"Jumlah Kejadian Penanggulangan Bencana","realisasi":64006250,"anggaran":85341666.66666667},{"nama":"Terselenggaranya pelayanan tanggap darurat bencana","realisasi":12027560,"anggaran":12027560}]}]}],"2":[{"nama":"Penanggulangan Bencana, Keadaan Darurat Dan Mendesak Desa","kegiatan":[{"nama":"Keadaan Mendesak","uraian":[{"nama":"Jumlah Kejadian Keadaan Mendesak","realisasi":306000000,"anggaran":306000000}]}]}],"3":[{"nama":"Pembinaan Kemasyarakatan Desa","kegiatan":[{"nama":"Penyelenggaraan Festival Kesenian, Adat\/Kebudayaan, dan Keagamaan (perayaan hari kemerdekaan, hari besar keagamaan, dll) tingkat Desa","uraian":[{"nama":"Jumlah Frekwensi Penyelenggaraan Festival Kesenian, Adat\/Kebudayaan, dan Keagamaan (perayaan hari kemerdekaan, hari besar keagamaan, dll) tingkat Desa","realisasi":38061376,"anggaran":38061376}]},{"nama":"Penyediaan Pos Kesiapsiagaan Bencana Skala Lokal Desa","uraian":[{"nama":"Pos Kesiapsiagaan Bencana Skala Lokal Desa","realisasi":24827500,"anggaran":24827500}]},{"nama":"Pembinaan Group Kesenian dan Kebudayaan Tingkat Desa","uraian":[{"nama":"Terselenggaranya Pembinaan Group Kesenian dan Kebudayaan Tingkat Desa","realisasi":20365500,"anggaran":20365500}]}]},{"nama":"Penanggulangan Bencana, Keadaan Darurat Dan Mendesak Desa","kegiatan":[{"nama":"Keadaan Mendesak","uraian":[{"nama":"Jumlah Kejadian Keadaan Mendesak","realisasi":81000000,"anggaran":81000000}]},{"nama":"Penanggulangan Bencana","uraian":[{"nama":"Terselenggaranya pelayanan tanggap darurat bencana","realisasi":39268200,"anggaran":39268200}]}]},{"nama":"Pelaksanaan Pembangunan Desa","kegiatan":[{"nama":"Penyelenggaraan Posyandu (Makanan Tambahan, Kelas Ibu Hamil, Kelas Lansia, Insentif Kader Posyandu)","uraian":[{"nama":"Terselenggaranya Operasional Pos Kesehatan Desa (PKD)\/Polindes Milik Desa Lainnya","realisasi":20680000,"anggaran":20680000}]},{"nama":"Penyelenggaraan Desa Siaga Kesehatan","uraian":[{"nama":"Penyelenggaraan Desa Siaga Kesehatan Lainnya","realisasi":8627250,"anggaran":8627250}]}]}]}}]}}