{"success":true,"data":{"total_record":1,"per_page":1,"total_page":1,"current_page":1,"result":[{"kode_PUM":"3318022002","provinsi":"Jawa Tengah","kabupaten_kota":"Kab. Pati","kecamatan":"Kayen","desa_kelurahan":"Durensawit","updated_date":null,"pagu":1090744000,"total_penyaluran":1090744000,"penyaluran":{"1":{"realisasi":218148800,"tanggal_realisasi":"05-APR-18"},"2":{"realisasi":436297600,"tanggal_realisasi":"28-JUN-18"},"3":{"realisasi":436297600,"tanggal_realisasi":"16-OCT-18"}},"penyerapan":{"1":[{"nama":"Pelaksanaan Pembangunan Desa","kegiatan":[{"nama":"Pembangunan\/Rehabilitasi\/Peningkatan\/Pengerasan Jalan Desa **","uraian":[{"nama":"Jalan Desa","realisasi":67148800,"anggaran":223829333.33333334}]},{"nama":"Pembangunan\/Rehabilitasi\/Peningkatan Sanitasi Permukiman (Gorong-gorong, Selokan, Parit, dll., diluar prasarana jalan) **","uraian":[{"nama":"Sanitasi Permukiman (Gorong-gorong, Selokan, Parit, dll., diluar prasarana jalan)","realisasi":57000000,"anggaran":57000000}]}]},{"nama":"Pemberdayaan Masyarakat Desa","kegiatan":[{"nama":"Peningkatan kapasitas perangkat Desa","uraian":[{"nama":"Jumlah Peserta Peningkatan kapasitas perangkat Desa","realisasi":4000000,"anggaran":4000000}]}]}],"2":[{"nama":"Pelaksanaan Pembangunan Desa","kegiatan":[{"nama":"Pembangunan\/Rehabilitasi\/Peningkatan\/Pengerasan Jalan Desa **","uraian":[{"nama":"Jalan Desa","realisasi":178000000,"anggaran":178000000}]}]}],"3":[{"nama":"Pelaksanaan Pembangunan Desa","kegiatan":[{"nama":"Pembangunan\/Rehabilitasi\/Peningkatan Balai Desa\/Balai Kemasyarakatan**","uraian":[{"nama":"Gedung Balai Desa\/Balai Kemasyrakatan","realisasi":399980000,"anggaran":399980000}]},{"nama":"Pembangunan\/Rehabilitasi\/Peningkatan\/Pengerasan Jalan Desa **","uraian":[{"nama":"Jalan Desa","realisasi":341703500,"anggaran":341703500}]}]},{"nama":"Pemberdayaan Masyarakat Desa","kegiatan":[{"nama":"Penyertaan Modal BUM Desa","uraian":[{"nama":"Jumlah Penyertaan Modal BUM Desa","realisasi":20000000,"anggaran":20000000}]}]}]}}]}}