{"success":true,"data":{"total_record":1,"per_page":1,"total_page":1,"current_page":1,"result":[{"kode_PUM":"3303092009","provinsi":"Jawa Tengah","kabupaten_kota":"Kab. Purbalingga","kecamatan":"Bobotsari","desa_kelurahan":"Karangtalun","updated_date":null,"pagu":1026362000,"total_penyaluran":1026362000,"penyaluran":{"1":{"realisasi":205272400,"tanggal_realisasi":"17-APR-18"},"2":{"realisasi":410544800,"tanggal_realisasi":"04-JUL-18"},"3":{"realisasi":410544800,"tanggal_realisasi":"16-NOV-18"}},"penyerapan":{"1":[{"nama":"Pemberdayaan Masyarakat Desa","kegiatan":[{"nama":"Pemeliharan Saluran Irigasi Tersier\/Sederhana","uraian":[{"nama":"Pemeliharan Saluran Irigasi Tersier\/Sederhana","realisasi":103035500,"anggaran":190806481.4814815}]}]}],"2":[{"nama":"Pembinaan Kemasyarakatan Desa","kegiatan":[{"nama":"Pembinaan Karang Taruna\/Klub Kepemudaan\/Klub Olah raga","uraian":[{"nama":"Terselenggaranya Pembinaan Karang Taruna\/Klub Kepemudaan\/Klub Olah raga","realisasi":4200000,"anggaran":4200000}]},{"nama":"Pembinaan Group Kesenian dan Kebudayaan Tingkat Desa","uraian":[{"nama":"Terselenggaranya Pembinaan Group Kesenian dan Kebudayaan Tingkat Desa","realisasi":6900000,"anggaran":6900000}]}]},{"nama":"Pelaksanaan Pembangunan Desa","kegiatan":[{"nama":"Penyelenggaraan Posyandu (Makanan Tambahan, Kelas Ibu Hamil, Kelas Lansia, Insentif Kader Posyandu)","uraian":[{"nama":"Terselenggaranya Operasional Pos Kesehatan Desa (PKD)\/Polindes Milik Desa Lainnya","realisasi":4440000,"anggaran":4440000}]},{"nama":"Penyelenggaraan Pos Kesehatan Desa (PKD)\/Polindes Milik Desa (Obat-obatan; Tambahan Insentif Bidan Desa\/Perawat Desa; Penyediaan Pelayanan KB dan Alat Kontrasepsi bagi Keluarga Miskin, dst)","uraian":[{"nama":"Terselenggaranya Operasional Pos Kesehatan Desa (PKD)\/Polindes Milik Desa Lainnya","realisasi":10650000,"anggaran":10650000}]},{"nama":"Pemeliharaan Sarana\/Prasarana Posyandu\/Polindes\/PKD","uraian":[{"nama":"Pemeliharaan Sarana\/Prasarana Posyandu\/Polindes\/PKD","realisasi":5696400,"anggaran":5696400}]},{"nama":"Pembangunan\/Rehabilitasi\/Peningkatan\/Pengerasan Jalan Lingkungan Permukiman\/Gang **","uraian":[{"nama":"Rehabilitasi\/Peningkatan\/Pengerasan Jalan Lingkungan Permukiman\/ Gang","realisasi":32447000,"anggaran":32447000}]},{"nama":"Pemeliharaan Jalan Desa","uraian":[{"nama":"Pemeilharaan Jalan Desa","realisasi":16054000,"anggaran":107026666.66666667}]},{"nama":"Penyelenggaraan PAUD\/TK\/TPA\/TKA\/TPQ\/Madrasah Non-Formal Milik Desa** (Bantuan Honor Pengajar, Pakaian Seragam, Operasional, dst)","uraian":[{"nama":"Operasional PAUD\/TK\/TPA\/TKA\/TPQ\/Madrasah Non-Formal Milik Desa","realisasi":9300000,"anggaran":9300000}]},{"nama":"Pemeliharaan Sarana dan Prasarana PAUD\/TK\/TPA\/TKA\/TPQ\/Madrasah Non-Formal Milik Desa**","uraian":[{"nama":"Pemeliharaan Sarana dan Prasarana PAUD\/TK\/TPA\/TKA\/TPQ\/Madrasah Non-Formal Milik Desa","realisasi":4850000,"anggaran":4850000}]}]},{"nama":"Pemberdayaan Masyarakat Desa","kegiatan":[{"nama":"Pemeliharan Saluran Irigasi Tersier\/Sederhana","uraian":[{"nama":"Pemeliharan Saluran Irigasi Tersier\/Sederhana","realisasi":60221000,"anggaran":60221000}]}]}],"3":[{"nama":"Pelaksanaan Pembangunan Desa","kegiatan":[{"nama":"Pemeliharaan Jalan Desa","uraian":[{"nama":"Pemeilharaan Jalan Desa","realisasi":497785850,"anggaran":497785850}]}]},{"nama":"Pemberdayaan Masyarakat Desa","kegiatan":[{"nama":"Pemeliharan Saluran Irigasi Tersier\/Sederhana","uraian":[{"nama":"Pemeliharan Saluran Irigasi Tersier\/Sederhana","realisasi":56078000,"anggaran":56078000}]},{"nama":"Kegiatan Pembangunan \/ Pemeliharaan Saluran Irigasi","uraian":[{"nama":"Saluran Irigasi","realisasi":111668750,"anggaran":111668750}]}]}]}}]}}