{"success":true,"data":{"total_record":1,"per_page":1,"total_page":1,"current_page":1,"result":[{"kode_PUM":"3322022009","provinsi":"Jawa Tengah","kabupaten_kota":"Kab. Semarang","kecamatan":"Tengaran","desa_kelurahan":"Karangduren","updated_date":null,"pagu":889813000,"total_penyaluran":889813000,"penyaluran":{"1":{"realisasi":177963000,"tanggal_realisasi":"08-MAR-19"},"2":{"realisasi":355925000,"tanggal_realisasi":"01-JUL-19"},"3":{"realisasi":355925000,"tanggal_realisasi":"22-OCT-19"}},"penyerapan":{"1":[{"nama":"Pelaksanaan Pembangunan Desa","kegiatan":[{"nama":"Pembangunan\/Rehabilitasi\/Peningkatan\/Pengerasan Jalan Desa **","uraian":[{"nama":"Rehabilitasi\/Peningkatan\/Pengerasan Jalan Desa","realisasi":114965000,"anggaran":114965000}]}]}],"2":[{"nama":"Pelaksanaan Pembangunan Desa","kegiatan":[{"nama":"Pembangunan\/Rehabilitasi\/Peningkatan\/Pengerasan Jalan Desa **","uraian":[{"nama":"Rehabilitasi\/Peningkatan\/Pengerasan Jalan Desa","realisasi":109158000,"anggaran":109158000}]}]}],"3":[]}}]}}