{"success":true,"data":{"total_record":1,"per_page":1,"total_page":1,"current_page":1,"result":[{"kode_PUM":"3306062006","provinsi":"Jawa Tengah","kabupaten_kota":"Kab. Purworejo","kecamatan":"Purworejo","desa_kelurahan":"Wonoroto","updated_date":null,"pagu":659597000,"total_penyaluran":659597000,"penyaluran":{"1":{"realisasi":131919400,"tanggal_realisasi":"11-APR-18"},"2":{"realisasi":263838800,"tanggal_realisasi":"25-JUL-18"},"3":{"realisasi":263838800,"tanggal_realisasi":"11-OCT-18"}},"penyerapan":{"1":[{"nama":"Pelaksanaan Pembangunan Desa","kegiatan":[{"nama":"Pembangunan\/Rehabilitasi\/Peningkatan\/Pengadaan Sarana\/Prasarana\/Alat Peraga Edukatif (APE) PAUD\/ TK\/TPA\/TKA\/TPQ\/Madrasah Non-Formal Milik Desa**","uraian":[{"nama":"Gedung\/Bangunan PAUD\/ TK\/TPA\/TKA\/TPQ\/Madrasah Non-Formal Milik Desa","realisasi":122448900,"anggaran":122448900}]}]}],"2":[{"nama":"Pemberdayaan Masyarakat Desa","kegiatan":[{"nama":"Pembangunan\/Rehabilitasi\/Peningkatan Pasar Desa\/Kios milik Desa **","uraian":[{"nama":"Pasar Desa","realisasi":87110800,"anggaran":145184666.66666666}]}]},{"nama":"Pelaksanaan Pembangunan Desa","kegiatan":[{"nama":"Pembangunan Tembok Penahan Tanah","uraian":[{"nama":"Pembangunan Tembok Penahan Tanah","realisasi":37937000,"anggaran":63228333.333333336}]},{"nama":"Pembangunan\/Rehabilitasi\/Peningkatan Prasarana Jalan Desa (Gorong-gorong, Selokan, Box\/Slab Culvert, Drainase, Prasarana Jalan lain) **","uraian":[{"nama":"Prasarana Jalan Desa (Gorong-gorong, Selokan, Box\/Slab Culvert, Drainase, Prasarana Jalan lain)","realisasi":6605700,"anggaran":6605700}]},{"nama":"Pembangunan\/Rehabilitasi\/Peningkatan\/Pengerasan Jalan Desa **","uraian":[{"nama":"Jalan Desa","realisasi":68395500,"anggaran":91194000}]}]}],"3":[]}}]}}