{"success":true,"data":{"total_record":1,"per_page":1,"total_page":1,"current_page":1,"result":[{"kode_PUM":"3310182018","provinsi":"Jawa Tengah","kabupaten_kota":"Kab. Klaten","kecamatan":"Karanganom","desa_kelurahan":"Pondok","updated_date":null,"pagu":712940000,"total_penyaluran":712940000,"penyaluran":{"1":{"realisasi":142588000,"tanggal_realisasi":"08-MAY-18"},"2":{"realisasi":285176000,"tanggal_realisasi":"04-JUL-18"},"3":{"realisasi":285176000,"tanggal_realisasi":"29-OCT-18"}},"penyerapan":{"1":[{"nama":"Pelaksanaan Pembangunan Desa","kegiatan":[{"nama":"Pembangunan Tembok Penahan Tanah","uraian":[{"nama":"Pembangunan Tembok Penahan Tanah","realisasi":69290000,"anggaran":69290000}]}]},{"nama":"Pemberdayaan Masyarakat Desa","kegiatan":[{"nama":"Peningkatan kapasitas perangkat Desa","uraian":[{"nama":"Jumlah Peserta Peningkatan kapasitas perangkat Desa","realisasi":3500000,"anggaran":3500000}]}]}],"2":[{"nama":"Pelaksanaan Pembangunan Desa","kegiatan":[{"nama":"Pembangunan\/Rehabilitasi\/Peningkatan\/Pengerasan Jalan Desa **","uraian":[{"nama":"Rehabilitasi\/Peningkatan\/Pengerasan Jalan Desa","realisasi":138829000,"anggaran":138829000}]},{"nama":"Pembangunan Tembok Penahan Tanah","uraian":[{"nama":"Pembangunan Tembok Penahan Tanah","realisasi":12639000,"anggaran":12639000}]}]},{"nama":"Penyelenggaraan Pemerintahan Desa","kegiatan":[{"nama":"Pembangunan\/Rehabilitasi\/Peningkatan Gedung\/Prasarana Kantor Desa**","uraian":[{"nama":"Rehabilitasi\/Peningkatan Bangunan","realisasi":134812500,"anggaran":134812500}]}]}],"3":[{"nama":"Pelaksanaan Pembangunan Desa","kegiatan":[{"nama":"Pengembangan dan Pembinaan Sanggar Seni dan Belajar","uraian":[{"nama":"Sarana Sanggar Seni dan Belajar Lainnya","realisasi":15000000,"anggaran":15000000}]},{"nama":"Penyelenggaraan Pos Kesehatan Desa (PKD)\/Polindes Milik Desa (Obat-obatan; Tambahan Insentif Bidan Desa\/Perawat Desa; Penyediaan Pelayanan KB dan Alat Kontrasepsi bagi Keluarga Miskin, dst)","uraian":[{"nama":"Terselenggaranya Operasional Pos Kesehatan Desa (PKD)\/Polindes Milik Desa Lainnya","realisasi":53365000,"anggaran":53365000}]},{"nama":"Dukungan pelaksanaan program Pembangunan\/Rehab Rumah Tidak Layak Huni (RTLH) GAKIN (pemetaan, validasi, dll)","uraian":[{"nama":"Jumlah Rumah Tidak Layak Huni (RTLH)","realisasi":10000000,"anggaran":10000000}]},{"nama":"Pemeliharaan Fasilitas Jamban Umum\/MCK umum, dll","uraian":[{"nama":"Pemeliharaan Fasilitas Jamban Umum\/MCK umum, dll","realisasi":12500500,"anggaran":12500500}]},{"nama":"Penyelenggaraan PAUD\/TK\/TPA\/TKA\/TPQ\/Madrasah Non-Formal Milik Desa** (Bantuan Honor Pengajar, Pakaian Seragam, Operasional, dst)","uraian":[{"nama":"Operasional PAUD\/TK\/TPA\/TKA\/TPQ\/Madrasah Non-Formal Milik Desa","realisasi":37650000,"anggaran":37650000}]},{"nama":"Pemeliharaan Prasarana Jalan Desa (Gorong-gorong, Selokan, Box\/Slab Culvert, Drainase, Prasarana Jalan lain)","uraian":[{"nama":"Pemeliharaan Prasarana Jalan Desa (Gorong-gorong, Selokan, Box\/Slab Culvert, Drainase, Prasarana Jalan lain)","realisasi":7771000,"anggaran":7771000}]}]},{"nama":"Pembinaan Kemasyarakatan Desa","kegiatan":[{"nama":"Kegiatan Pembinaan keterampilan produktif bagi keluarga prasejahtera","uraian":[{"nama":"Penyediaan Tenaga Kerja Terampil, siap pakai","realisasi":9290000,"anggaran":9290000}]},{"nama":"Peningkata Kapasitas Masyarakat","uraian":[{"nama":"Masyarakat mandiri\/Terampil","realisasi":5500000,"anggaran":5500000}]}]},{"nama":"Pemberdayaan Masyarakat Desa","kegiatan":[{"nama":"Peningkatan Produksi Tanaman Pangan (Alat Produksi dan pengolahan pertanian, penggilingan Padi\/jagung, dll)","uraian":[{"nama":"Jumlah alat produksi dan pengolahan pertanian yang diserahkan","realisasi":11740000,"anggaran":11740000}]},{"nama":"Peningkatan kapasitas perangkat Desa","uraian":[{"nama":"Jumlah Peserta Peningkatan kapasitas perangkat Desa","realisasi":6000000,"anggaran":6000000}]}]}]}}]}}