{"success":true,"data":{"total_record":1,"per_page":1,"total_page":1,"current_page":1,"result":[{"kode_PUM":"3329172007","provinsi":"Jawa Tengah","kabupaten_kota":"Kab. Brebes","kecamatan":"Banjarharjo","desa_kelurahan":"Cibuniwangi","updated_date":null,"pagu":1403825000,"total_penyaluran":1403825000,"penyaluran":{"1":{"realisasi":280765000,"tanggal_realisasi":"31-MAY-19"},"2":{"realisasi":561530000,"tanggal_realisasi":"23-SEP-19"},"3":{"realisasi":561530000,"tanggal_realisasi":"03-DEC-19"}},"penyerapan":{"1":[{"nama":"Pelaksanaan Pembangunan Desa","kegiatan":[{"nama":"Pembangunan\/Rehabilitasi\/Peningkatan\/Pengerasan Jalan Desa **","uraian":[{"nama":"Jalan Desa","realisasi":27874000,"anggaran":27874000}]},{"nama":"Pembangunan\/Rehabilitasi\/Peningkatan Fasilitas Pengelolaan Sampah Desa\/Permukiman (Penampungan, Bank Sampah, dll)**","uraian":[{"nama":"Fasilitas Pengelolaan Sampah Desa\/Permukiman (Penampungan, Bank Sampah, dll)","realisasi":49796000,"anggaran":49796000}]},{"nama":"Pembangunan\/Rehabilitasi\/Peningkatan Prasarana Jalan Desa (Gorong-gorong, Selokan, Box\/Slab Culvert, Drainase, Prasarana Jalan lain) **","uraian":[{"nama":"Prasarana Jalan Desa (Gorong-gorong, Selokan, Box\/Slab Culvert, Drainase, Prasarana Jalan lain)","realisasi":71188000,"anggaran":71188000}]},{"nama":"Pembangunan\/Rehabilitasi\/Peningkatan\/Pengerasan Jembatan Milik Desa **","uraian":[{"nama":"Rehabilitasi\/Peningkatan Jembatan Desa","realisasi":36585000,"anggaran":36585000}]}]},{"nama":"Penyelenggaraan Pemerintahan Desa","kegiatan":[{"nama":"Pemetaan dan Analisis Kemiskinan Desa secara Partisipatif","uraian":[{"nama":"Dokumen Pemetaan Kemiskinan Desa secara Partisipatif","realisasi":16514000,"anggaran":16514000}]},{"nama":"Pengembangan Sistem Informasi Desa ","uraian":[{"nama":"Terciptanya Sistem Informasi Desa","realisasi":7800000,"anggaran":78000000}]}]}],"2":[{"nama":"Pelaksanaan Pembangunan Desa","kegiatan":[{"nama":"Pembangunan\/Rehabilitasi\/Peningkatan\/Pengerasan Jalan Desa **","uraian":[{"nama":"Jalan Desa","realisasi":214980000,"anggaran":307114285.71428573}]},{"nama":"Penyelenggaraan Posyandu (Makanan Tambahan, Kelas Ibu Hamil, Kelas Lansia, Insentif Kader Posyandu)","uraian":[{"nama":"Terselenggaranya Operasional Pos Kesehatan Desa (PKD)\/Polindes Milik Desa Lainnya","realisasi":24000000,"anggaran":24000000}]},{"nama":"Dukungan Pendidikan bagi Siswa Miskin\/Berprestasi","uraian":[{"nama":"Jumlah Siswa Penerima Bea Siswa","realisasi":16000000,"anggaran":16000000}]}]},{"nama":"Penyelenggaraan Pemerintahan Desa","kegiatan":[{"nama":"Pemetaan dan Analisis Kemiskinan Desa secara Partisipatif","uraian":[{"nama":"Dokumen Pemetaan Kemiskinan Desa secara Partisipatif","realisasi":23426000,"anggaran":23426000}]}]}],"3":[]}}]}}