{"success":true,"data":{"total_record":1,"per_page":1,"total_page":1,"current_page":1,"result":[{"kode_PUM":"3323062004","provinsi":"Jawa Tengah","kabupaten_kota":"Kab. Temanggung","kecamatan":"Kandangan","desa_kelurahan":"Wadas","updated_date":null,"pagu":912971000,"total_penyaluran":137188400,"penyaluran":{"1":{"realisasi":137188400,"tanggal_realisasi":"04-MAR-21"},"2":{"realisasi":0,"tanggal_realisasi":""},"3":{"realisasi":0,"tanggal_realisasi":""}},"penyerapan":{"1":[{"nama":"Penanggulangan Bencana, Keadaan Darurat Dan Mendesak Desa","kegiatan":[{"nama":"Keadaan Mendesak","uraian":[{"nama":"Jumlah Kejadian Keadaan Mendesak","realisasi":228000000,"anggaran":570000000}]}]},{"nama":"Pelaksanaan Pembangunan Desa","kegiatan":[{"nama":"Penyelenggaraan Posyandu (Makanan Tambahan, Kelas Ibu Hamil, Kelas Lansia, Insentif Kader Posyandu)","uraian":[{"nama":"Makanan Tambahan","realisasi":15000000,"anggaran":15000000}]},{"nama":"Pengelolaan dan Pembuatan Jaringan\/Instalasi Komunikasi dan Informasi Lokal Desa","uraian":[{"nama":"Poster\/Baliho\/Lainnya atas ke masyarakat Informasi APBDes, LPJ, dan lainnya","realisasi":2236363,"anggaran":2236363}]},{"nama":"Pengelolaan Lingkungan Hidup Desa","uraian":[{"nama":"Terselenggaranya Penghijauan Desa","realisasi":10000000,"anggaran":10000000}]},{"nama":"Penyelenggaraan Desa Siaga Kesehatan","uraian":[{"nama":"Bantuan dan dukungan untuk kelancaran Testing\/Tracing\/Treatment Kesehatan dari Kementerian Kesehatan dan Pemerintah daerah","realisasi":418000,"anggaran":836000}]}]},{"nama":"Pembinaan Kemasyarakatan Desa","kegiatan":[{"nama":"Pengadaan\/Penyelenggaraan Pos Keamanan Desa (pembangunan pos, pengawasan pelaksanaan jadwal ronda\/patroli dll) **","uraian":[{"nama":"Penyelenggaraan Pos Keaamanan Desa","realisasi":14882272,"anggaran":49607573.333333336}]}]},{"nama":"Penyelenggaraan Pemerintahan Desa","kegiatan":[{"nama":"Pemetaan dan Analisis Kemiskinan Desa secara Partisipatif","uraian":[{"nama":"Dokumen Pemetaan Kemiskinan Desa secara Partisipatif","realisasi":39016300,"anggaran":39016300}]}]}],"2":[{"nama":"Penanggulangan Bencana, Keadaan Darurat Dan Mendesak Desa","kegiatan":[{"nama":"Keadaan Mendesak","uraian":[{"nama":"Jumlah Kejadian Keadaan Mendesak","realisasi":410400000,"anggaran":547200000}]}]}],"3":[]}}]}}