{"success":true,"data":{"total_record":1,"per_page":1,"total_page":1,"current_page":1,"result":[{"kode_PUM":"3311062008","provinsi":"Jawa Tengah","kabupaten_kota":"Kab. Sukoharjo","kecamatan":"Bendosari","desa_kelurahan":"Paluhombo","updated_date":null,"pagu":1000184000,"total_penyaluran":1000184000,"penyaluran":{"1":{"realisasi":201933000,"tanggal_realisasi":"23-MAY-18"},"2":{"realisasi":396087000,"tanggal_realisasi":"25-JUL-18"},"3":{"realisasi":402164000,"tanggal_realisasi":"26-OCT-18"}},"penyerapan":{"1":[{"nama":"Pelaksanaan Pembangunan Desa","kegiatan":[{"nama":"Pembangunan\/Rehabilitasi\/Peningkatan\/Pengerasan Jalan Desa **","uraian":[{"nama":"Jalan Desa","realisasi":59623000,"anggaran":59623000}]}]}],"2":[{"nama":"Pembinaan Kemasyarakatan Desa","kegiatan":[{"nama":"Pembangunan\/Rehabilitasi\/Peningkatan Sarana dan Prasarana Kepemudaan dan Olah Raga Milik Desa**","uraian":[{"nama":"Rehabilitasi\/Peningkatan Sarana dan Prasarana Kepemudaan dan Olah Raga Milik Desa","realisasi":199710000,"anggaran":199710000}]}]},{"nama":"Pelaksanaan Pembangunan Desa","kegiatan":[{"nama":"Pembangunan Tembok Penahan Tanah","uraian":[{"nama":"Pembangunan Tembok Penahan Tanah","realisasi":111175000,"anggaran":111175000}]},{"nama":"Pembangunan\/Rehabilitasi\/Peningkatan\/Pengerasan Jalan Lingkungan Permukiman\/Gang **","uraian":[{"nama":"Jalan Pemukiman\/Gang","realisasi":81290000,"anggaran":81290000}]}]}],"3":[{"nama":"Pelaksanaan Pembangunan Desa","kegiatan":[{"nama":"Pembangunan Tembok Penahan Tanah","uraian":[{"nama":"Pembangunan Tembok Penahan Tanah","realisasi":36298000,"anggaran":36298000}]},{"nama":"Pembangunan\/Rehabilitasi\/Peningkatan Sumber Air Bersih Milik Desa (Mata Air\/Tandon Penampungan Air Hujan\/Sumur Bor, dll)**","uraian":[{"nama":"Sumber Air Bersih Milik Desa (Mata Air\/Tandon Penampungan Air Hujan\/Sumur Bor, dll)","realisasi":300000000,"anggaran":300000000}]}]}]}}]}}