{"success":true,"data":{"total_record":1,"per_page":1,"total_page":1,"current_page":1,"result":[{"kode_PUM":"3306022020","provinsi":"Jawa Tengah","kabupaten_kota":"Kab. Purworejo","kecamatan":"Ngombol","desa_kelurahan":"Rasukan","updated_date":null,"pagu":653271000,"total_penyaluran":653271000,"penyaluran":{"1":{"realisasi":130654200,"tanggal_realisasi":"16-MAR-18"},"2":{"realisasi":261308400,"tanggal_realisasi":"06-JUL-18"},"3":{"realisasi":261308400,"tanggal_realisasi":"24-OCT-18"}},"penyerapan":{"1":[{"nama":"Pelaksanaan Pembangunan Desa","kegiatan":[{"nama":"Penyelenggaraan Posyandu (Makanan Tambahan, Kelas Ibu Hamil, Kelas Lansia, Insentif Kader Posyandu)","uraian":[{"nama":"Terselenggaranya Operasional Pos Kesehatan Desa (PKD)\/Polindes Milik Desa Lainnya","realisasi":5108600,"anggaran":11880465.11627907}]},{"nama":"Pembangunan\/Rehabilitasi\/Peningkatan\/Pengadaan Sarana\/Prasarana\/Alat Peraga Edukatif (APE) PAUD\/ TK\/TPA\/TKA\/TPQ\/Madrasah Non-Formal Milik Desa**","uraian":[{"nama":"Gedung\/Bangunan PAUD\/ TK\/TPA\/TKA\/TPQ\/Madrasah Non-Formal Milik Desa","realisasi":96197600,"anggaran":96197600}]}]},{"nama":"Pemberdayaan Masyarakat Desa","kegiatan":[{"nama":"Pemeliharan Saluran Irigasi Tersier\/Sederhana","uraian":[{"nama":"Pemeliharan Saluran Irigasi Tersier\/Sederhana","realisasi":29348000,"anggaran":419257142.85714287}]}]}],"2":[{"nama":"Pelaksanaan Pembangunan Desa","kegiatan":[{"nama":"Penyelenggaraan Posyandu (Makanan Tambahan, Kelas Ibu Hamil, Kelas Lansia, Insentif Kader Posyandu)","uraian":[{"nama":"Terselenggaranya Operasional Pos Kesehatan Desa (PKD)\/Polindes Milik Desa Lainnya","realisasi":6733200,"anggaran":6733200}]}]},{"nama":"Pemberdayaan Masyarakat Desa","kegiatan":[{"nama":"Pemeliharan Saluran Irigasi Tersier\/Sederhana","uraian":[{"nama":"Pemeliharan Saluran Irigasi Tersier\/Sederhana","realisasi":254575200,"anggaran":353576666.6666667}]}]}],"3":[{"nama":"Pelaksanaan Pembangunan Desa","kegiatan":[{"nama":"Pembangunan Tembok Penahan Tanah","uraian":[{"nama":"Pembangunan Tembok Penahan Tanah","realisasi":96698500,"anggaran":96698500}]},{"nama":"Pembangunan\/Rehabilitasi\/Peningkatan\/Pengerasan Jalan Lingkungan Permukiman\/Gang **","uraian":[{"nama":"Rehabilitasi\/Peningkatan\/Pengerasan Jalan Lingkungan Permukiman\/ Gang","realisasi":72415500,"anggaran":72415500}]}]},{"nama":"Pemberdayaan Masyarakat Desa","kegiatan":[{"nama":"Pemeliharan Saluran Irigasi Tersier\/Sederhana","uraian":[{"nama":"Pemeliharan Saluran Irigasi Tersier\/Sederhana","realisasi":92194400,"anggaran":92194400}]}]}]}}]}}