{"success":true,"data":{"total_record":1,"per_page":1,"total_page":1,"current_page":1,"result":[{"kode_PUM":"3321132009","provinsi":"Jawa Tengah","kabupaten_kota":"Kab. Demak","kecamatan":"Wedung","desa_kelurahan":"Bungo","updated_date":null,"pagu":1243227000,"total_penyaluran":844581600,"penyaluran":{"1":{"realisasi":422290800,"tanggal_realisasi":"26-FEB-21"},"2":{"realisasi":422290800,"tanggal_realisasi":"16-JUN-21"},"3":{"realisasi":0,"tanggal_realisasi":""}},"penyerapan":{"1":[{"nama":"Pelaksanaan Pembangunan Desa","kegiatan":[{"nama":"Pemeliharaan Jalan Lingkungan Permukiman\/Gang","uraian":[{"nama":"Pemeliharaan Jalan Lingkungan Permukiman\/Gang","realisasi":11683000,"anggaran":11683000}]},{"nama":"Pemeliharaan Jembatan Milik Desa","uraian":[{"nama":"Jembatan Milik Desa","realisasi":33397000,"anggaran":33397000}]},{"nama":"Pemeliharaan Sanitasi Permukiman (Gorong-gorong, Selokan, Parit, dll., diluar prasarana jalan)","uraian":[{"nama":"Pemeliharaan Sanitasi","realisasi":14000000,"anggaran":14000000}]},{"nama":"Pembangunan\/Rehabilitasi\/Peningkatan Sanitasi Permukiman (Gorong-gorong, Selokan, Parit, dll., diluar prasarana jalan) **","uraian":[{"nama":"Sanitasi Permukiman (Gorong-gorong, Selokan, Parit, dll., diluar prasarana jalan)","realisasi":49677000,"anggaran":49677000}]},{"nama":"Penyelenggaraan Posyandu (Makanan Tambahan, Kelas Ibu Hamil, Kelas Lansia, Insentif Kader Posyandu)","uraian":[{"nama":"Makanan Tambahan","realisasi":96050000,"anggaran":96050000}]},{"nama":"Pembangunan\/Rehabilitas\/Peningkatan Fasilitas Jamban Umum\/MCK umum, dll **","uraian":[{"nama":"Fasilitas Jamban Umum\/MCK umum, dll","realisasi":35000000,"anggaran":35000000}]},{"nama":"Dukungan pelaksanaan program Pembangunan\/Rehab Rumah Tidak Layak Huni (RTLH) GAKIN (pemetaan, validasi, dll)","uraian":[{"nama":"Jumlah Rumah Tidak Layak Huni (RTLH)","realisasi":75000000,"anggaran":75000000}]}]},{"nama":"Penanggulangan Bencana, Keadaan Darurat Dan Mendesak Desa","kegiatan":[{"nama":"Keadaan Darurat","uraian":[{"nama":"Jumlah Kejadian Keadaan Darurat","realisasi":66202800,"anggaran":66202800}]},{"nama":"Keadaan Mendesak","uraian":[{"nama":"Jumlah Kejadian Keadaan Mendesak","realisasi":15000000,"anggaran":15000000}]}]}],"2":[{"nama":"Pelaksanaan Pembangunan Desa","kegiatan":[{"nama":"Pembangunan\/Rehabilitasi\/Peningkatan\/Pengerasan Jalan Desa **","uraian":[{"nama":"Jalan Desa","realisasi":44600000,"anggaran":44600000}]},{"nama":"Pengelolaan Perpustakaan Milik Desa (Pengadaan Buku-buku Bacaan, Honor Penjaga untuk Perpustakaan\/Taman Bacaan Desa)","uraian":[{"nama":"Terselenggaranya Operasional Perpustakaan\/Taman Bacaan\/Sanggar Belajar Lainnya","realisasi":49747000,"anggaran":49747000}]},{"nama":"Pembangunan\/Rehabilitasi\/Peningkatan\/Pengerasan Jalan Usaha Tani **","uraian":[{"nama":"Pembangunan Jalan Usaha Tani","realisasi":69661000,"anggaran":69661000}]},{"nama":"Dukungan Penyelenggaraan PAUD (APE, Sarana PAUD, dst)","uraian":[{"nama":"Dukungan Penyelenggaraan PAUD non Milik Desa","realisasi":5000000,"anggaran":5000000}]},{"nama":"Penyelenggaraan Posyandu (Makanan Tambahan, Kelas Ibu Hamil, Kelas Lansia, Insentif Kader Posyandu)","uraian":[{"nama":"Makanan Tambahan","realisasi":36570000,"anggaran":36570000}]}]},{"nama":"Pemberdayaan Masyarakat Desa","kegiatan":[{"nama":"Pengadaan, Pembangunan, Pemanfaatan dan Pemeliharaan sarana prasarana pemasaran Produk","uraian":[{"nama":"Pengadaan, Pembangunan, Pemanfaatan dan Pemeliharaan sarana prasarana pemasaran Produk","realisasi":62359000,"anggaran":62359000}]},{"nama":"Pelatihan Pengelolaan BUM Desa (Pelatihan yang dilaksanakan oleh Desa)","uraian":[{"nama":"Jumlah Peserta Pelatihan Pengelolaan BUM Desa (Pelatihan yang dilaksanakan oleh Desa)","realisasi":35000000,"anggaran":35000000}]},{"nama":"Pelatihan\/Penyuluhan Pemberdayaan Perempuan","uraian":[{"nama":"Jumlah Frekwensi Pelatihan\/Penyuluhan Pemberdayaan Perempuan","realisasi":10000000,"anggaran":10000000}]},{"nama":"Pembangunan\/Rehabilitasi\/Peningkatan Pelabuhan Perikanan Sungai\/Kecil Milik Desa**","uraian":[{"nama":"Pelabuhan Perikanan Sungai\/Kecil Milik Desa","realisasi":27831000,"anggaran":27831000}]}]},{"nama":"Pembinaan Kemasyarakatan Desa","kegiatan":[{"nama":"Penyediaan Pos Kesiapsiagaan Bencana Skala Lokal Desa","uraian":[{"nama":"Pos Kesiapsiagaan Bencana Skala Lokal Desa","realisasi":75093400,"anggaran":75093400}]}]},{"nama":"Penanggulangan Bencana, Keadaan Darurat Dan Mendesak Desa","kegiatan":[{"nama":"Keadaan Mendesak","uraian":[{"nama":"Jumlah Kejadian Keadaan Mendesak","realisasi":15000000,"anggaran":15000000}]}]}],"3":[{"nama":"Penanggulangan Bencana, Keadaan Darurat Dan Mendesak Desa","kegiatan":[{"nama":"Keadaan Mendesak","uraian":[{"nama":"Tambahan Bantuan Langsung Tunai (BLT) - Dana Desa","realisasi":15000000,"anggaran":15000000}]},{"nama":"Penanggulangan Bencana","uraian":[{"nama":"Terselenggaranya pelayanan tanggap darurat bencana","realisasi":65400,"anggaran":65400}]},{"nama":"Keadaan Darurat","uraian":[{"nama":"Jumlah Kejadian Keadaan Darurat","realisasi":30000000,"anggaran":30000000}]}]},{"nama":"Pemberdayaan Masyarakat Desa","kegiatan":[{"nama":"Pelatihan\/Penyuluhan Pemberdayaan Perempuan","uraian":[{"nama":"Jumlah Frekwensi Pelatihan\/Penyuluhan Pemberdayaan Perempuan","realisasi":30000000,"anggaran":30000000}]},{"nama":"Pelatihan\/Bimtek\/Pengenalan Tekonologi Tepat Guna untuk Pertanian\/Peternakan **","uraian":[{"nama":"Jumlah Peserta Pelatihan\/Bimtek\/Pengenalan Tekonologi Tepat Guna untuk Pertanian\/Peternakan","realisasi":41000000,"anggaran":41000000}]}]},{"nama":"Pelaksanaan Pembangunan Desa","kegiatan":[{"nama":"Penyelenggaraan PAUD\/TK\/TPA\/TKA\/TPQ\/Madrasah Non-Formal Milik Desa** (Bantuan Honor Pengajar, Pakaian Seragam, Operasional, dst)","uraian":[{"nama":"Operasional PAUD\/TK\/TPA\/TKA\/TPQ\/Madrasah Non-Formal Milik Desa","realisasi":5000000,"anggaran":5000000}]},{"nama":"Dukungan Pendidikan bagi Siswa Miskin\/Berprestasi","uraian":[{"nama":"Jumlah Siswa Penerima Bea Siswa","realisasi":13200000,"anggaran":13200000}]},{"nama":"Pembangunan\/Rehabilitasi\/Peningkatan Sistem Pembuangan Air Limbah (Drainase, Air limbah Rumah Tangga)**","uraian":[{"nama":"Rehabilitasi\/Peningkatan Sistem Pembuangan Air Limbah (Drainase, Air limbah Rumah Tangga)","realisasi":70000000,"anggaran":70000000}]},{"nama":"Penyelenggaraan Posyandu (Makanan Tambahan, Kelas Ibu Hamil, Kelas Lansia, Insentif Kader Posyandu)","uraian":[{"nama":"Makanan Tambahan","realisasi":24380000,"anggaran":24380000}]}]}]}}]}}