{"success":true,"data":{"total_record":1,"per_page":1,"total_page":1,"current_page":1,"result":[{"kode_PUM":"3325042003","provinsi":"Jawa Tengah","kabupaten_kota":"Kab. Batang","kecamatan":"Reban","desa_kelurahan":"Cablikan","updated_date":null,"pagu":902596000,"total_penyaluran":1263634400,"penyaluran":{"1":{"realisasi":180519200,"tanggal_realisasi":"26-APR-18"},"2":{"realisasi":361038400,"tanggal_realisasi":"05-JUL-18"},"3":{"realisasi":361038400,"tanggal_realisasi":"15-NOV-18"}},"penyerapan":{"1":[{"nama":"Pelaksanaan Pembangunan Desa","kegiatan":[{"nama":"Pembangunan\/Rehabilitasi\/Peningkatan\/Pengerasan Jalan Desa **","uraian":[{"nama":"Jalan Desa","realisasi":163269200,"anggaran":163269200}]},{"nama":"Penyelenggaraan PAUD\/TK\/TPA\/TKA\/TPQ\/Madrasah Non-Formal Milik Desa** (Bantuan Honor Pengajar, Pakaian Seragam, Operasional, dst)","uraian":[{"nama":"Operasional PAUD\/TK\/TPA\/TKA\/TPQ\/Madrasah Non-Formal Milik Desa","realisasi":3000000,"anggaran":3000000}]}]}],"2":[{"nama":"Pelaksanaan Pembangunan Desa","kegiatan":[{"nama":"Pembangunan\/Rehabilitasi\/Peningkatan\/Pengerasan Jalan Desa **","uraian":[{"nama":"Jalan Desa","realisasi":122810300,"anggaran":122810300}]}]}],"3":[{"nama":"Pelaksanaan Pembangunan Desa","kegiatan":[{"nama":"Pembangunan\/Rehabilitasi\/Peningkatan\/Pengerasan Jalan Desa **","uraian":[{"nama":"Jalan Desa","realisasi":105659900,"anggaran":105659900}]}]},{"nama":"Pemberdayaan Masyarakat Desa","kegiatan":[{"nama":"Pelatihan\/Penyuluhan Pemberdayaan Perempuan","uraian":[{"nama":"Jumlah Frekwensi Pelatihan\/Penyuluhan Pemberdayaan Perempuan","realisasi":3000000,"anggaran":3000000}]},{"nama":"Kegiatan Pembentukan dan Fasilitasi Kader Pembangunan dan Pemberdayaan Masyarakat Desa","uraian":[{"nama":"Honor tenaga pendamping\/Kader pembangunan","realisasi":3000000,"anggaran":3000000}]}]},{"nama":"Pembinaan Kemasyarakatan Desa","kegiatan":[{"nama":"Pembinaan Karang Taruna\/Klub Kepemudaan\/Klub Olah raga","uraian":[{"nama":"Terselenggaranya Pembinaan Karang Taruna\/Klub Kepemudaan\/Klub Olah raga","realisasi":3000000,"anggaran":3000000}]}]}]}}]}}