{"success":true,"data":{"total_record":1,"per_page":1,"total_page":1,"current_page":1,"result":[{"kode_PUM":"3328032007","provinsi":"Jawa Tengah","kabupaten_kota":"Kab. Tegal","kecamatan":"Bojong","desa_kelurahan":"Bojong","updated_date":null,"pagu":1503909000,"total_penyaluran":120312720,"penyaluran":{"1":{"realisasi":120312720,"tanggal_realisasi":"09-MAR-21"},"2":{"realisasi":0,"tanggal_realisasi":""},"3":{"realisasi":0,"tanggal_realisasi":""}},"penyerapan":{"1":[{"nama":"Penyelenggaraan Pemerintahan Desa","kegiatan":[{"nama":"Pemetaan dan Analisis Kemiskinan Desa secara Partisipatif","uraian":[{"nama":"Dokumen Pemetaan Kemiskinan Desa secara Partisipatif","realisasi":21450000,"anggaran":21450000}]},{"nama":"Penyediaan Insentif\/Operasional RT\/RW","uraian":[{"nama":"Operasional RT\/RW","realisasi":1184400,"anggaran":1184400}]}]},{"nama":"Pelaksanaan Pembangunan Desa","kegiatan":[{"nama":"Pemeliharaan Sarana dan Prasarana Perpustakaan\/Taman Bacaan Desa\/ Sanggar Belajar Milik Desa **","uraian":[{"nama":"Pemeliharaan Sarana dan Prasarana Perpustakaan\/Taman Bacaan Desa\/ Sanggar Belajar Milik Desa","realisasi":20000000,"anggaran":20000000}]},{"nama":"Pemeliharaan Jalan Desa","uraian":[{"nama":"Pemeilharaan Jalan Desa","realisasi":205912000,"anggaran":205912000}]},{"nama":"Penyelenggaraan Posyandu (Makanan Tambahan, Kelas Ibu Hamil, Kelas Lansia, Insentif Kader Posyandu)","uraian":[{"nama":"Terselenggaranya Operasional Pos Kesehatan Desa (PKD)\/Polindes Milik Desa Lainnya","realisasi":5920000,"anggaran":5920000}]},{"nama":"Penyelenggaraan PAUD\/TK\/TPA\/TKA\/TPQ\/Madrasah Non-Formal Milik Desa** (Bantuan Honor Pengajar, Pakaian Seragam, Operasional, dst)","uraian":[{"nama":"Operasional PAUD\/TK\/TPA\/TKA\/TPQ\/Madrasah Non-Formal Milik Desa","realisasi":112500000,"anggaran":112500000}]}]},{"nama":"Penanggulangan Bencana, Keadaan Darurat Dan Mendesak Desa","kegiatan":[{"nama":"Keadaan Darurat","uraian":[{"nama":"Jumlah Kejadian Keadaan Darurat","realisasi":4700000,"anggaran":15666666.666666666}]},{"nama":"Keadaan Mendesak","uraian":[{"nama":"Jumlah Kejadian Keadaan Mendesak","realisasi":17400000,"anggaran":17400000}]}]}],"2":[{"nama":"Penanggulangan Bencana, Keadaan Darurat Dan Mendesak Desa","kegiatan":[{"nama":"Keadaan Mendesak","uraian":[{"nama":"Jumlah Kejadian Keadaan Mendesak","realisasi":17400000,"anggaran":17400000}]}]}],"3":[]}}]}}