{"success":true,"data":{"total_record":1,"per_page":1,"total_page":1,"current_page":1,"result":[{"kode_PUM":"3311052009","provinsi":"Jawa Tengah","kabupaten_kota":"Kab. Sukoharjo","kecamatan":"Nguter","desa_kelurahan":"Kedungwinong","updated_date":null,"pagu":1059812000,"total_penyaluran":1059812000,"penyaluran":{"1":{"realisasi":211652200,"tanggal_realisasi":"26-JUL-19"},"2":{"realisasi":424137000,"tanggal_realisasi":"09-AUG-19"},"3":{"realisasi":424022800,"tanggal_realisasi":"12-DEC-19"}},"penyerapan":{"1":[{"nama":"Pelaksanaan Pembangunan Desa","kegiatan":[{"nama":"Pembangunan\/Rehabilitasi\/Peningkatan\/Pengerasan Jalan Desa **","uraian":[{"nama":"Rehabilitasi\/Peningkatan\/Pengerasan Jalan Desa","realisasi":58138200,"anggaran":58138200}]}]}],"2":[{"nama":"Pelaksanaan Pembangunan Desa","kegiatan":[{"nama":"Pembangunan\/Rehabilitasi\/Peningkatan Prasarana Jalan Desa (Gorong-gorong, Selokan, Box\/Slab Culvert, Drainase, Prasarana Jalan lain) **","uraian":[{"nama":"Rehabilitasi\/Peningkatan Prasarana Jalan Desa (Gorong-gorong, Selokan, Box\/Slab Culvert, Drainase, Prasarana Jalan lain)","realisasi":40526000,"anggaran":40526000}]},{"nama":"Pembangunan\/Rehabilitasi\/Peningkatan\/Pengerasan Jalan Desa **","uraian":[{"nama":"Rehabilitasi\/Peningkatan\/Pengerasan Jalan Desa","realisasi":20971400,"anggaran":20971400}]}]}],"3":[]}}]}}