{"success":true,"data":{"total_record":1,"per_page":1,"total_page":1,"current_page":1,"result":[{"kode_PUM":"3323062002","provinsi":"Jawa Tengah","kabupaten_kota":"Kab. Temanggung","kecamatan":"Kandangan","desa_kelurahan":"Baledu","updated_date":null,"pagu":832171000,"total_penyaluran":624128250,"penyaluran":{"1":{"realisasi":337191200,"tanggal_realisasi":"22-APR-20"},"2":{"realisasi":124825650,"tanggal_realisasi":"20-MAY-20"},"3":{"realisasi":162111400,"tanggal_realisasi":"16-NOV-20"}},"penyerapan":{"1":[{"nama":"Penanggulangan Bencana, Keadaan Darurat Dan Mendesak Desa","kegiatan":[{"nama":"Keadaan Darurat","uraian":[{"nama":"Jumlah Kejadian Keadaan Darurat","realisasi":69210000,"anggaran":69210000}]}]}],"2":[{"nama":"Penyelenggaraan Pemerintahan Desa","kegiatan":[{"nama":"Pemetaan dan Analisis Kemiskinan Desa secara Partisipatif","uraian":[{"nama":"Dokumen Pemetaan Kemiskinan Desa secara Partisipatif","realisasi":6000000,"anggaran":6000000}]},{"nama":"Penyusunan\/Pendataan\/Pemutakhiran Profil Desa (profil kependudukan dan potensi desa)**","uraian":[{"nama":"Dokumen Profil Desa (profil kependudukan dan potensi desa)","realisasi":4000000,"anggaran":4000000}]},{"nama":"Penyusunan Dokumen Perencanaan Desa (RPJMDes\/RKPDes,dll)","uraian":[{"nama":"Dokumen Perencanaan Desa ","realisasi":12775000,"anggaran":25550000}]}]},{"nama":"Pelaksanaan Pembangunan Desa","kegiatan":[{"nama":"Pengelolaan dan Pembuatan Jaringan\/Instalasi Komunikasi dan Informasi Lokal Desa","uraian":[{"nama":"Poster\/Baliho\/Lainnya atas ke masyarakat Informasi APBDes, LPJ, dan lainnya","realisasi":5640000,"anggaran":5640000}]}]},{"nama":"Pembinaan Kemasyarakatan Desa","kegiatan":[{"nama":"Pemeliharaan Sarana dan Prasarana Kepemudaan dan Olah Raga Milik Desa**","uraian":[{"nama":"Pemeliharaan Sarana dan Prasarana Kepemudaan dan Olah Raga Milik Desa","realisasi":62895500,"anggaran":62895500}]}]},{"nama":"Penanggulangan Bencana, Keadaan Darurat Dan Mendesak Desa","kegiatan":[{"nama":"Keadaan Mendesak","uraian":[{"nama":"Jumlah Kejadian Keadaan Mendesak","realisasi":372600000,"anggaran":414000000}]}]}],"3":[{"nama":"Pelaksanaan Pembangunan Desa","kegiatan":[{"nama":"Penyuluhan dan Pelatihan Pendidikan bagi Masyarakat","uraian":[{"nama":"Jumlah Peserta Penyuluhan dan Pelatihan Pendidikan bagi Masyarakat","realisasi":13000000,"anggaran":13000000}]},{"nama":"Penyuluhan dan Pelatihan Bidang Kesehatan (untuk Masyarakat, Tenaga Kesehatan, Kader Kesehatan, dll)","uraian":[{"nama":"Jumlah Peserta Penyuluhan dan Pelatihan Bidang Kesehatan","realisasi":14546000,"anggaran":14546000}]},{"nama":"Penyelenggaraan Pos Kesehatan Desa (PKD)\/Polindes Milik Desa (Obat-obatan; Tambahan Insentif Bidan Desa\/Perawat Desa; Penyediaan Pelayanan KB dan Alat Kontrasepsi bagi Keluarga Miskin, dst)","uraian":[{"nama":"Terselenggaranya Operasional Pos Kesehatan Desa (PKD)\/Polindes Milik Desa Lainnya","realisasi":15200000,"anggaran":15200000}]},{"nama":"Penyelenggaraan Posyandu (Makanan Tambahan, Kelas Ibu Hamil, Kelas Lansia, Insentif Kader Posyandu)","uraian":[{"nama":"Makanan Tambahan","realisasi":8500000,"anggaran":8500000}]},{"nama":"Pembangunan\/Rehabilitasi\/Peningkatan\/Pengadaan Sarana\/Prasarana Posyandu\/Polindes\/PKD **","uraian":[{"nama":"Sarana Posyandu\/Polindes\/PKD Lainnya","realisasi":40035400,"anggaran":40035400}]},{"nama":"Penyelenggaraan Desa Siaga Kesehatan","uraian":[{"nama":"Penyelenggaraan Desa Siaga Kesehatan Lainnya","realisasi":20000000,"anggaran":20000000}]},{"nama":"Penyelenggaraan PAUD\/TK\/TPA\/TKA\/TPQ\/Madrasah Non-Formal Milik Desa** (Bantuan Honor Pengajar, Pakaian Seragam, Operasional, dst)","uraian":[{"nama":"Operasional PAUD\/TK\/TPA\/TKA\/TPQ\/Madrasah Non-Formal Milik Desa","realisasi":14500000,"anggaran":14500000}]}]},{"nama":"Pemberdayaan Masyarakat Desa","kegiatan":[{"nama":"Pelatihan\/Penyuluhan Pemberdayaan Perempuan","uraian":[{"nama":"Jumlah Frekwensi Pelatihan\/Penyuluhan Pemberdayaan Perempuan","realisasi":13000000,"anggaran":13000000}]},{"nama":"Pelatihan dan Penguatan Penyandang Difabel (penyandang disabilitas)","uraian":[{"nama":"Jumlah Frekwensi Pelatihan dan Penguatan Penyandang Difabel (penyandang disabilitas)","realisasi":6000000,"anggaran":6000000}]},{"nama":"Peningkatan Produksi Tanaman Pangan (Alat Produksi dan pengolahan pertanian, penggilingan Padi\/jagung, dll)","uraian":[{"nama":"Jumlah alat produksi dan pengolahan pertanian yang diserahkan","realisasi":15000000,"anggaran":15000000}]}]},{"nama":"Pembinaan Kemasyarakatan Desa","kegiatan":[{"nama":"Pembinaan Group Kesenian dan Kebudayaan Tingkat Desa","uraian":[{"nama":"Terselenggaranya Pembinaan Group Kesenian dan Kebudayaan Tingkat Desa","realisasi":20000000,"anggaran":20000000}]},{"nama":"Pelatihan\/Penyuluhan\/Sosialisasi kepada Masyarakat di Bidang Hukum dan Pelindungan Masyarakat","uraian":[{"nama":"Jumlah Peserta Pelatihan\/Penyuluhan\/Sosialisasi kepada Masyarakat di Bidang Hukum dan Pelindungan Masyarakat","realisasi":10000000,"anggaran":10000000}]},{"nama":"Pelatihan Kesiapsiagaan\/Tanggap Bencana Skala Lokal Desa","uraian":[{"nama":"Jumlah Peserta Pelatihan Kesiapsiagaan\/Tanggap Bencana Skala Lokal Desa","realisasi":10000000,"anggaran":10000000}]}]},{"nama":"Pembiayaan","kegiatan":[{"nama":"Penyertaan Modal","uraian":[{"nama":"Penyertaan Modal BUMDes","realisasi":72164000,"anggaran":72164000}]}]},{"nama":"Penyelenggaraan Pemerintahan Desa","kegiatan":[{"nama":"Pengembangan Sistem Informasi Desa ","uraian":[{"nama":"Terciptanya Sistem Informasi Desa","realisasi":5000000,"anggaran":5000000}]},{"nama":"Penyusunan Dokumen Perencanaan Desa (RPJMDes\/RKPDes,dll)","uraian":[{"nama":"Dokumen Perencanaan Desa ","realisasi":33250000,"anggaran":33250000}]}]}]}}]}}