{"success":true,"data":{"total_record":1,"per_page":1,"total_page":1,"current_page":1,"result":[{"kode_PUM":"3305072020","provinsi":"Jawa Tengah","kabupaten_kota":"Kab. Kebumen","kecamatan":"Ambal","desa_kelurahan":"Sidoluhur","updated_date":null,"pagu":1075034000,"total_penyaluran":1075034000,"penyaluran":{"1":{"realisasi":215006800,"tanggal_realisasi":"17-MAY-19"},"2":{"realisasi":430013600,"tanggal_realisasi":"08-AUG-19"},"3":{"realisasi":430013600,"tanggal_realisasi":"12-NOV-19"}},"penyerapan":{"1":[{"nama":"Pelaksanaan Pembangunan Desa","kegiatan":[{"nama":"Pemeliharaan Jalan Desa","uraian":[{"nama":"Pemeilharaan Jalan Desa","realisasi":209100200,"anggaran":209100200}]},{"nama":"Penyelenggaraan Posyandu (Makanan Tambahan, Kelas Ibu Hamil, Kelas Lansia, Insentif Kader Posyandu)","uraian":[{"nama":"Makanan Tambahan","realisasi":5906000,"anggaran":19051612.903225806}]}]}],"2":[{"nama":"Pelaksanaan Pembangunan Desa","kegiatan":[{"nama":"Pemeliharaan Jalan Desa","uraian":[{"nama":"Pemeilharaan Jalan Desa","realisasi":72266900,"anggaran":206476857.14285713}]},{"nama":"Pembangunan\/Rehabilitas\/Peningkatan Fasilitas Jamban Umum\/MCK umum, dll **","uraian":[{"nama":"Fasilitas Jamban Umum\/MCK umum, dll","realisasi":36000000,"anggaran":60000000}]},{"nama":"Dukungan pelaksanaan program Pembangunan\/Rehab Rumah Tidak Layak Huni (RTLH) GAKIN (pemetaan, validasi, dll)","uraian":[{"nama":"Jumlah Rumah Tidak Layak Huni (RTLH)","realisasi":60000000,"anggaran":80000000}]},{"nama":"Pemeliharaan Prasarana Jalan Desa (Gorong-gorong, Selokan, Box\/Slab Culvert, Drainase, Prasarana Jalan lain)","uraian":[{"nama":"Pemeliharaan Prasarana Jalan Desa (Gorong-gorong, Selokan, Box\/Slab Culvert, Drainase, Prasarana Jalan lain)","realisasi":207296200,"anggaran":246781190.47619048}]}]},{"nama":"Pemberdayaan Masyarakat Desa","kegiatan":[{"nama":"Pemeliharan Saluran Irigasi Tersier\/Sederhana","uraian":[{"nama":"Pemeliharan Saluran Irigasi Tersier\/Sederhana","realisasi":54420000,"anggaran":92237288.13559322}]}]}],"3":[]}}]}}