{"success":true,"data":{"total_record":1,"per_page":1,"total_page":1,"current_page":1,"result":[{"kode_PUM":"3316092005","provinsi":"Jawa Tengah","kabupaten_kota":"Kab. Blora","kecamatan":"Blora","desa_kelurahan":"Andongrejo","updated_date":null,"pagu":911191000,"total_penyaluran":911191000,"penyaluran":{"1":{"realisasi":182238200,"tanggal_realisasi":"12-APR-18"},"2":{"realisasi":364476400,"tanggal_realisasi":"30-JUL-18"},"3":{"realisasi":364476400,"tanggal_realisasi":"06-DEC-18"}},"penyerapan":{"1":[{"nama":"Pelaksanaan Pembangunan Desa","kegiatan":[{"nama":"Pembangunan\/Rehabilitasi\/Peningkatan\/Pengerasan Jalan Desa **","uraian":[{"nama":"Rehabilitasi\/Peningkatan\/Pengerasan Jalan Desa","realisasi":182238200,"anggaran":182238200}]}]}],"2":[{"nama":"Pelaksanaan Pembangunan Desa","kegiatan":[{"nama":"Pembangunan\/Rehabilitasi\/Peningkatan\/Pengerasan Jalan Desa **","uraian":[{"nama":"Jalan Desa","realisasi":285726400,"anggaran":285726400}]},{"nama":"Penyuluhan dan Pelatihan Bidang Kesehatan (untuk Masyarakat, Tenaga Kesehatan, Kader Kesehatan, dll)","uraian":[{"nama":"Jumlah Peserta Penyuluhan dan Pelatihan Bidang Kesehatan","realisasi":2250000,"anggaran":2250000}]},{"nama":"Pembangunan\/Rehabilitasi\/Peningkatan Sambungan Air Bersih ke Rumah Tangga (pipanisasi, dll) **","uraian":[{"nama":"Sambungan Air Bersih ke Rumah Tangga (pipanisasi, dll)","realisasi":65000000,"anggaran":65000000}]}]},{"nama":"Pemberdayaan Masyarakat Desa","kegiatan":[{"nama":"Pelatihan\/Penyuluhan Pemberdayaan Perempuan","uraian":[{"nama":"Jumlah Frekwensi Pelatihan\/Penyuluhan Pemberdayaan Perempuan","realisasi":11500000,"anggaran":11500000}]}]}],"3":[{"nama":"Pemberdayaan Masyarakat Desa","kegiatan":[{"nama":"Pelatihan\/Bimtek\/Pengenalan Tekonologi Tepat Guna untuk Perikanan Darat\/Nelayan **","uraian":[{"nama":"Jumlah Peserta Pelatihan\/Bimtek\/Pengenalan Teknologi Tepat Guna untuk Perikanan Darat\/Nelayan","realisasi":16000000,"anggaran":16000000}]},{"nama":"Pelatihan\/Penyuluhan Pemberdayaan Perempuan","uraian":[{"nama":"Jumlah Frekwensi Pelatihan\/Penyuluhan Pemberdayaan Perempuan","realisasi":11500000,"anggaran":11500000}]}]},{"nama":"Pelaksanaan Pembangunan Desa","kegiatan":[{"nama":"Pembangunan\/Rehabilitasi\/Peningkatan\/Pengerasan Jalan Desa **","uraian":[{"nama":"Jalan Desa","realisasi":208763400,"anggaran":208763400}]},{"nama":"Penyelenggaraan PAUD\/TK\/TPA\/TKA\/TPQ\/Madrasah Non-Formal Milik Desa** (Bantuan Honor Pengajar, Pakaian Seragam, Operasional, dst)","uraian":[{"nama":"Operasional PAUD\/TK\/TPA\/TKA\/TPQ\/Madrasah Non-Formal Milik Desa","realisasi":9963000,"anggaran":9963000}]},{"nama":"Penyelenggaraan Posyandu (Makanan Tambahan, Kelas Ibu Hamil, Kelas Lansia, Insentif Kader Posyandu)","uraian":[{"nama":"Terselenggaranya Operasional Pos Kesehatan Desa (PKD)\/Polindes Milik Desa Lainnya","realisasi":23850000,"anggaran":23850000}]},{"nama":"Pembangunan\/Rehabilitas\/Peningkatan Fasilitas Jamban Umum\/MCK umum, dll **","uraian":[{"nama":"Fasilitas Jamban Umum\/MCK umum, dll","realisasi":45150000,"anggaran":45150000}]},{"nama":"Penyelenggaraan Pos Kesehatan Desa (PKD)\/Polindes Milik Desa (Obat-obatan; Tambahan Insentif Bidan Desa\/Perawat Desa; Penyediaan Pelayanan KB dan Alat Kontrasepsi bagi Keluarga Miskin, dst)","uraian":[{"nama":"Terselenggaranya Operasional Pos Kesehatan Desa (PKD)\/Polindes Milik Desa Lainnya","realisasi":7500000,"anggaran":7500000}]}]},{"nama":"Penyelenggaraan Pemerintahan Desa","kegiatan":[{"nama":"Pengembangan Sistem Informasi Desa ","uraian":[{"nama":"Terciptanya Sistem Informasi Desa","realisasi":1200000,"anggaran":1200000}]}]}]}}]}}