{"success":true,"data":{"total_record":1,"per_page":1,"total_page":1,"current_page":1,"result":[{"kode_PUM":"3326182004","provinsi":"Jawa Tengah","kabupaten_kota":"Kab. Pekalongan","kecamatan":"Karangdadap","desa_kelurahan":"Kedungkebo","updated_date":null,"pagu":862247000,"total_penyaluran":862247000,"penyaluran":{"1":{"realisasi":172449400,"tanggal_realisasi":"22-APR-19"},"2":{"realisasi":344898800,"tanggal_realisasi":"28-MAY-19"},"3":{"realisasi":344898800,"tanggal_realisasi":"26-SEP-19"}},"penyerapan":{"1":[{"nama":"Pelaksanaan Pembangunan Desa","kegiatan":[{"nama":"Pembangunan\/Rehabilitasi\/Peningkatan\/Pengadaan Sarana\/Prasarana\/Alat Peraga Edukatif (APE) PAUD\/ TK\/TPA\/TKA\/TPQ\/Madrasah Non-Formal Milik Desa**","uraian":[{"nama":"Rehabilitasi\/Peningkatan Sarana\/Prasarana\/APE PAUD\/ TK\/TPA\/TKA\/TPQ\/Madrasah Non-Formal Milik Desa","realisasi":172449400,"anggaran":172449400}]}]}],"2":[{"nama":"Pelaksanaan Pembangunan Desa","kegiatan":[{"nama":"Pembangunan\/Rehabilitasi\/Peningkatan Prasarana Jalan Desa (Gorong-gorong, Selokan, Box\/Slab Culvert, Drainase, Prasarana Jalan lain) **","uraian":[{"nama":"Prasarana Jalan Desa (Gorong-gorong, Selokan, Box\/Slab Culvert, Drainase, Prasarana Jalan lain)","realisasi":9406000,"anggaran":9406000}]},{"nama":"Pemeliharaan Jalan Desa","uraian":[{"nama":"Pemeilharaan Jalan Desa","realisasi":99573000,"anggaran":99573000}]},{"nama":"Pemeliharaan Jalan Lingkungan Permukiman\/Gang","uraian":[{"nama":"Pemeliharaan Jalan Lingkungan Permukiman\/Gang","realisasi":31369000,"anggaran":31369000}]}]}],"3":[]}}]}}